Metadata-Version: 2.1
Name: password-generator-lib
Version: 1.0.0
Summary: A library for generating secure passwords
Home-page: https://github.com/salimovm/password-generator
Author: Mahammad Salimov
Author-email: salimovm.7@gmail.com
License: MIT
Platform: UNKNOWN
Classifier: Programming Language :: Python :: 3
Classifier: License :: OSI Approved :: MIT License
Classifier: Operating System :: OS Independent
Requires-Dist: black (==23.3.0)
Requires-Dist: click (==8.1.3)
Requires-Dist: colorama (==0.4.6)
Requires-Dist: mypy-extensions (==1.0.0)
Requires-Dist: packaging (==23.1)
Requires-Dist: pathspec (==0.11.1)
Requires-Dist: platformdirs (==3.5.0)
Requires-Dist: tomli (==2.0.1)
Requires-Dist: typing-extensions (==4.5.0)
